sbmlplot/__init__.py
sbmlplot/sbmlplot.py
sbmlplot/test.py
sbmlplot-0.0.7.data/scripts/test.py
sbmlplot-0.0.7.dist-info/LICENSE
sbmlplot-0.0.7.dist-info/METADATA
sbmlplot-0.0.7.dist-info/WHEEL
sbmlplot-0.0.7.dist-info/top_level.txt
sbmlplot-0.0.7.dist-info/RECORD
