Metadata-Version: 2.1
Name: sbmlplot
Version: 0.0.7
Summary: Visualize the network of SBML models
Home-page: https://github.com/adelhpour/sbmlplot
Author: Adel Heydarabadipour
Author-email: ad.heydarabadi@gmail.com
License: MIT License
Platform: UNKNOWN
Classifier: Intended Audience :: Science/Research
Classifier: Programming Language :: Python
Classifier: License :: OSI Approved :: MIT License
Classifier: Operating System :: OS Independent
Requires-Python: >=3.7
License-File: LICENSE
Requires-Dist: libsbne
Requires-Dist: numpy
Requires-Dist: python-libsbml
Requires-Dist: webcolors
